{
  "pathToUnityExe": "/opt/unity/Editor/Unity",
  "pathToUnityHub": "",
  "userProjects": [],
  "unityEditors": [],
  "defaultProjectPath": "/root/.local/share/VRChatProjects",
  "lastUIState": 0,
  "skipUnityAutoFind": false,
  "userPackageFolders": [],
  "windowSize": 0,
  "skipRequirements": false,
  "lastNewsUpdate": "2023-02-24T09:06:22.1878864Z",
  "allowPii": false,
  "projectBackupPath": "/root/.local/share/VRChatCreatorCompanion/Project Backups",
  "showPrereleasePackages": false,
  "selectedProviders": 3,
  "userRepos": []
}
